{
    "subjects": [
        {
            "name": "nan",
            "teacher": "nan",
            "type": "nan"
        },
        {
            "name": "Эргономика ПО",
            "teacher": "Завьялов А.В.",
            "type": "лк"
        },
        {
            "name": "Эргономика ПО",
            "teacher": "Завьялов А.В.",
            "type": "пр"
        },
        {
            "name": "Проектирование ПИ ПС",
            "teacher": "Архипов С.Г.",
            "type": "лк+пр"
        },
        {
            "name": "Проектирование ПИ ПС",
            "teacher": "Архипов С.Г.",
            "type": "пр"
        },
        {
            "name": "ПТП",
            "teacher": "nan",
            "type": "пр"
        },
        {
            "name": "СППМиИ",
            "teacher": "Худак Ю.И.",
            "type": "лк"
        },
        {
            "name": "СППМиИ",
            "teacher": "Худак Ю.И.",
            "type": "пр"
        },
        {
            "name": "Многокрит. обработка КИ",
            "teacher": "Шкутник Е.Э.",
            "type": "лк+пр"
        },
        {
            "name": "Многокрит. обработка КИ",
            "teacher": "Шкутник Е.Э.",
            "type": "пр"
        }
    ],
    "timetables": [
        {
            "days": [
                {
                    "lessons": [
                        {
                            "lessonNumber": 1,
                            "subjectIndex": 0,
                            "constraint": {
                                "type": [],
                                "weeks": []
                            },
                            "room": "nan",
                            "locationIndex": 0
                        },
                        {
                            "lessonNumber": 2,
                            "subjectIndex": 0,
                            "constraint": {
                                "type": [],
                                "weeks": []
                            },
                            "room": "nan",
                            "locationIndex": 0
                        },
                        {
                            "lessonNumber": 3,
                            "subjectIndex": 0,
                            "constraint": {
                                "type": [],
                                "weeks": []
                            },
                            "room": "nan",
                            "locationIndex": 0
                        },
                        {
                            "lessonNumber": 4,
                            "subjectIndex": 1,
                            "constraint": {
                                "type": [],
                                "weeks": []
                            },
                            "room": "Д",
                            "locationIndex": -1
                        },
                        {
                            "lessonNumber": 5,
                            "subjectIndex": 3,
                            "constraint": {
                                "type": [],
                                "weeks": []
                            },
                            "room": "Д",
                            "locationIndex": -1
                        },
                        {
                            "lessonNumber": 6,
                            "subjectIndex": 0,
                            "constraint": {
                                "type": [],
                                "weeks": []
                            },
                            "room": "nan",
                            "locationIndex": 0
                        }
                    ]
                },
                {
                    "lessons": [
                        {
                            "lessonNumber": 1,
                            "subjectIndex": 0,
                            "constraint": {
                                "type": [],
                                "weeks": []
                            },
                            "room": "nan",
                            "locationIndex": 0
                        },
                        {
                            "lessonNumber": 2,
                            "subjectIndex": 0,
                            "constraint": {
                                "type": [],
                                "weeks": []
                            },
                            "room": "nan",
                            "locationIndex": 0
                        },
                        {
                            "lessonNumber": 3,
                            "subjectIndex": 0,
                            "constraint": {
                                "type": [],
                                "weeks": []
                            },
                            "room": "nan",
                            "locationIndex": 0
                        },
                        {
                            "lessonNumber": 4,
                            "subjectIndex": 5,
                            "constraint": {
                                "type": [],
                                "weeks": []
                            },
                            "room": "Д",
                            "locationIndex": -1
                        },
                        {
                            "lessonNumber": 5,
                            "subjectIndex": 5,
                            "constraint": {
                                "type": [],
                                "weeks": []
                            },
                            "room": "Д",
                            "locationIndex": -1
                        },
                        {
                            "lessonNumber": 6,
                            "subjectIndex": 5,
                            "constraint": {
                                "type": [],
                                "weeks": []
                            },
                            "room": "Д",
                            "locationIndex": -1
                        }
                    ]
                },
                {
                    "lessons": [
                        {
                            "lessonNumber": 1,
                            "subjectIndex": 5,
                            "constraint": {
                                "type": [],
                                "weeks": []
                            },
                            "room": "Д",
                            "locationIndex": -1
                        },
                        {
                            "lessonNumber": 2,
                            "subjectIndex": 0,
                            "constraint": {
                                "type": [],
                                "weeks": []
                            },
                            "room": "nan",
                            "locationIndex": 0
                        },
                        {
                            "lessonNumber": 3,
                            "subjectIndex": 0,
                            "constraint": {
                                "type": [],
                                "weeks": []
                            },
                            "room": "nan",
                            "locationIndex": 0
                        },
                        {
                            "lessonNumber": 4,
                            "subjectIndex": 0,
                            "constraint": {
                                "type": [],
                                "weeks": []
                            },
                            "room": "nan",
                            "locationIndex": 0
                        },
                        {
                            "lessonNumber": 5,
                            "subjectIndex": 0,
                            "constraint": {
                                "type": [],
                                "weeks": []
                            },
                            "room": "nan",
                            "locationIndex": 0
                        },
                        {
                            "lessonNumber": 6,
                            "subjectIndex": 0,
                            "constraint": {
                                "type": [],
                                "weeks": []
                            },
                            "room": "nan",
                            "locationIndex": 0
                        }
                    ]
                },
                {
                    "lessons": [
                        {
                            "lessonNumber": 1,
                            "subjectIndex": 0,
                            "constraint": {
                                "type": [],
                                "weeks": []
                            },
                            "room": "nan",
                            "locationIndex": 0
                        },
                        {
                            "lessonNumber": 2,
                            "subjectIndex": 6,
                            "constraint": {
                                "type": [],
                                "weeks": []
                            },
                            "room": "Д",
                            "locationIndex": -1
                        },
                        {
                            "lessonNumber": 3,
                            "subjectIndex": 0,
                            "constraint": {
                                "type": [],
                                "weeks": []
                            },
                            "room": "nan",
                            "locationIndex": 0
                        },
                        {
                            "lessonNumber": 4,
                            "subjectIndex": 0,
                            "constraint": {
                                "type": [],
                                "weeks": []
                            },
                            "room": "nan",
                            "locationIndex": 0
                        },
                        {
                            "lessonNumber": 5,
                            "subjectIndex": 0,
                            "constraint": {
                                "type": [],
                                "weeks": []
                            },
                            "room": "nan",
                            "locationIndex": 0
                        },
                        {
                            "lessonNumber": 6,
                            "subjectIndex": 0,
                            "constraint": {
                                "type": [],
                                "weeks": []
                            },
                            "room": "nan",
                            "locationIndex": 0
                        }
                    ]
                },
                {
                    "lessons": [
                        {
                            "lessonNumber": 1,
                            "subjectIndex": 0,
                            "constraint": {
                                "type": [],
                                "weeks": []
                            },
                            "room": "nan",
                            "locationIndex": 0
                        },
                        {
                            "lessonNumber": 2,
                            "subjectIndex": 0,
                            "constraint": {
                                "type": [],
                                "weeks": []
                            },
                            "room": "nan",
                            "locationIndex": 0
                        },
                        {
                            "lessonNumber": 3,
                            "subjectIndex": 0,
                            "constraint": {
                                "type": [],
                                "weeks": []
                            },
                            "room": "nan",
                            "locationIndex": 0
                        },
                        {
                            "lessonNumber": 4,
                            "subjectIndex": 8,
                            "constraint": {
                                "type": [],
                                "weeks": []
                            },
                            "room": "Д",
                            "locationIndex": -1
                        },
                        {
                            "lessonNumber": 5,
                            "subjectIndex": 0,
                            "constraint": {
                                "type": [],
                                "weeks": []
                            },
                            "room": "nan",
                            "locationIndex": 0
                        },
                        {
                            "lessonNumber": 6,
                            "subjectIndex": 0,
                            "constraint": {
                                "type": [],
                                "weeks": []
                            },
                            "room": "nan",
                            "locationIndex": 0
                        }
                    ]
                },
                {
                    "lessons": [
                        {
                            "lessonNumber": 1,
                            "subjectIndex": 0,
                            "constraint": {
                                "type": [],
                                "weeks": []
                            },
                            "room": "nan",
                            "locationIndex": 0
                        },
                        {
                            "lessonNumber": 2,
                            "subjectIndex": 0,
                            "constraint": {
                                "type": [],
                                "weeks": []
                            },
                            "room": "nan",
                            "locationIndex": 0
                        },
                        {
                            "lessonNumber": 3,
                            "subjectIndex": 0,
                            "constraint": {
                                "type": [],
                                "weeks": []
                            },
                            "room": "nan",
                            "locationIndex": 0
                        },
                        {
                            "lessonNumber": 4,
                            "subjectIndex": 0,
                            "constraint": {
                                "type": [],
                                "weeks": []
                            },
                            "room": "nan",
                            "locationIndex": 0
                        },
                        {
                            "lessonNumber": 5,
                            "subjectIndex": 0,
                            "constraint": {
                                "type": [],
                                "weeks": []
                            },
                            "room": "nan",
                            "locationIndex": 0
                        },
                        {
                            "lessonNumber": 6,
                            "subjectIndex": 0,
                            "constraint": {
                                "type": [],
                                "weeks": []
                            },
                            "room": "nan",
                            "locationIndex": 0
                        }
                    ]
                }
            ]
        },
        {
            "days": [
                {
                    "lessons": [
                        {
                            "lessonNumber": 1,
                            "subjectIndex": 0,
                            "constraint": {
                                "type": [],
                                "weeks": []
                            },
                            "room": "nan",
                            "locationIndex": 0
                        },
                        {
                            "lessonNumber": 2,
                            "subjectIndex": 0,
                            "constraint": {
                                "type": [],
                                "weeks": []
                            },
                            "room": "nan",
                            "locationIndex": 0
                        },
                        {
                            "lessonNumber": 3,
                            "subjectIndex": 0,
                            "constraint": {
                                "type": [],
                                "weeks": []
                            },
                            "room": "nan",
                            "locationIndex": 0
                        },
                        {
                            "lessonNumber": 4,
                            "subjectIndex": 2,
                            "constraint": {
                                "type": [],
                                "weeks": []
                            },
                            "room": "Д",
                            "locationIndex": -1
                        },
                        {
                            "lessonNumber": 5,
                            "subjectIndex": 4,
                            "constraint": {
                                "type": [],
                                "weeks": []
                            },
                            "room": "Д",
                            "locationIndex": -1
                        },
                        {
                            "lessonNumber": 6,
                            "subjectIndex": 0,
                            "constraint": {
                                "type": [],
                                "weeks": []
                            },
                            "room": "nan",
                            "locationIndex": 0
                        }
                    ]
                },
                {
                    "lessons": [
                        {
                            "lessonNumber": 1,
                            "subjectIndex": 0,
                            "constraint": {
                                "type": [],
                                "weeks": []
                            },
                            "room": "nan",
                            "locationIndex": 0
                        },
                        {
                            "lessonNumber": 2,
                            "subjectIndex": 0,
                            "constraint": {
                                "type": [],
                                "weeks": []
                            },
                            "room": "nan",
                            "locationIndex": 0
                        },
                        {
                            "lessonNumber": 3,
                            "subjectIndex": 0,
                            "constraint": {
                                "type": [],
                                "weeks": []
                            },
                            "room": "nan",
                            "locationIndex": 0
                        },
                        {
                            "lessonNumber": 4,
                            "subjectIndex": 5,
                            "constraint": {
                                "type": [],
                                "weeks": []
                            },
                            "room": "Д",
                            "locationIndex": -1
                        },
                        {
                            "lessonNumber": 5,
                            "subjectIndex": 5,
                            "constraint": {
                                "type": [],
                                "weeks": []
                            },
                            "room": "Д",
                            "locationIndex": -1
                        },
                        {
                            "lessonNumber": 6,
                            "subjectIndex": 5,
                            "constraint": {
                                "type": [],
                                "weeks": []
                            },
                            "room": "Д",
                            "locationIndex": -1
                        }
                    ]
                },
                {
                    "lessons": [
                        {
                            "lessonNumber": 1,
                            "subjectIndex": 5,
                            "constraint": {
                                "type": [],
                                "weeks": []
                            },
                            "room": "Д",
                            "locationIndex": -1
                        },
                        {
                            "lessonNumber": 2,
                            "subjectIndex": 0,
                            "constraint": {
                                "type": [],
                                "weeks": []
                            },
                            "room": "nan",
                            "locationIndex": 0
                        },
                        {
                            "lessonNumber": 3,
                            "subjectIndex": 0,
                            "constraint": {
                                "type": [],
                                "weeks": []
                            },
                            "room": "nan",
                            "locationIndex": 0
                        },
                        {
                            "lessonNumber": 4,
                            "subjectIndex": 0,
                            "constraint": {
                                "type": [],
                                "weeks": []
                            },
                            "room": "nan",
                            "locationIndex": 0
                        },
                        {
                            "lessonNumber": 5,
                            "subjectIndex": 0,
                            "constraint": {
                                "type": [],
                                "weeks": []
                            },
                            "room": "nan",
                            "locationIndex": 0
                        },
                        {
                            "lessonNumber": 6,
                            "subjectIndex": 0,
                            "constraint": {
                                "type": [],
                                "weeks": []
                            },
                            "room": "nan",
                            "locationIndex": 0
                        }
                    ]
                },
                {
                    "lessons": [
                        {
                            "lessonNumber": 1,
                            "subjectIndex": 0,
                            "constraint": {
                                "type": [],
                                "weeks": []
                            },
                            "room": "nan",
                            "locationIndex": 0
                        },
                        {
                            "lessonNumber": 2,
                            "subjectIndex": 7,
                            "constraint": {
                                "type": [],
                                "weeks": []
                            },
                            "room": "Д",
                            "locationIndex": -1
                        },
                        {
                            "lessonNumber": 3,
                            "subjectIndex": 0,
                            "constraint": {
                                "type": [],
                                "weeks": []
                            },
                            "room": "nan",
                            "locationIndex": 0
                        },
                        {
                            "lessonNumber": 4,
                            "subjectIndex": 0,
                            "constraint": {
                                "type": [],
                                "weeks": []
                            },
                            "room": "nan",
                            "locationIndex": 0
                        },
                        {
                            "lessonNumber": 5,
                            "subjectIndex": 0,
                            "constraint": {
                                "type": [],
                                "weeks": []
                            },
                            "room": "nan",
                            "locationIndex": 0
                        },
                        {
                            "lessonNumber": 6,
                            "subjectIndex": 0,
                            "constraint": {
                                "type": [],
                                "weeks": []
                            },
                            "room": "nan",
                            "locationIndex": 0
                        }
                    ]
                },
                {
                    "lessons": [
                        {
                            "lessonNumber": 1,
                            "subjectIndex": 0,
                            "constraint": {
                                "type": [],
                                "weeks": []
                            },
                            "room": "nan",
                            "locationIndex": 0
                        },
                        {
                            "lessonNumber": 2,
                            "subjectIndex": 0,
                            "constraint": {
                                "type": [],
                                "weeks": []
                            },
                            "room": "nan",
                            "locationIndex": 0
                        },
                        {
                            "lessonNumber": 3,
                            "subjectIndex": 0,
                            "constraint": {
                                "type": [],
                                "weeks": []
                            },
                            "room": "nan",
                            "locationIndex": 0
                        },
                        {
                            "lessonNumber": 4,
                            "subjectIndex": 9,
                            "constraint": {
                                "type": [],
                                "weeks": []
                            },
                            "room": "Д",
                            "locationIndex": -1
                        },
                        {
                            "lessonNumber": 5,
                            "subjectIndex": 0,
                            "constraint": {
                                "type": [],
                                "weeks": []
                            },
                            "room": "nan",
                            "locationIndex": 0
                        },
                        {
                            "lessonNumber": 6,
                            "subjectIndex": 0,
                            "constraint": {
                                "type": [],
                                "weeks": []
                            },
                            "room": "nan",
                            "locationIndex": 0
                        }
                    ]
                },
                {
                    "lessons": [
                        {
                            "lessonNumber": 1,
                            "subjectIndex": 0,
                            "constraint": {
                                "type": [],
                                "weeks": []
                            },
                            "room": "nan",
                            "locationIndex": 0
                        },
                        {
                            "lessonNumber": 2,
                            "subjectIndex": 0,
                            "constraint": {
                                "type": [],
                                "weeks": []
                            },
                            "room": "nan",
                            "locationIndex": 0
                        },
                        {
                            "lessonNumber": 3,
                            "subjectIndex": 0,
                            "constraint": {
                                "type": [],
                                "weeks": []
                            },
                            "room": "nan",
                            "locationIndex": 0
                        },
                        {
                            "lessonNumber": 4,
                            "subjectIndex": 0,
                            "constraint": {
                                "type": [],
                                "weeks": []
                            },
                            "room": "nan",
                            "locationIndex": 0
                        },
                        {
                            "lessonNumber": 5,
                            "subjectIndex": 0,
                            "constraint": {
                                "type": [],
                                "weeks": []
                            },
                            "room": "nan",
                            "locationIndex": 0
                        },
                        {
                            "lessonNumber": 6,
                            "subjectIndex": 0,
                            "constraint": {
                                "type": [],
                                "weeks": []
                            },
                            "room": "nan",
                            "locationIndex": 0
                        }
                    ]
                }
            ]
        }
    ]
}