{
    "subjects": [
        {
            "name": "nan",
            "teacher": "nan",
            "type": "nan"
        },
        {
            "name": "История политических и правовых учений",
            "teacher": "Ахмедов Р.М.",
            "type": [
                "1",
                "лк,",
                "3",
                "пр"
            ]
        },
        {
            "name": "История и методология юридической ауки",
            "teacher": "Ахмедов Р.М.",
            "type": "пр"
        },
        {
            "name": "История и методология юридической науки",
            "teacher": "Ахмедов Р.М.",
            "type": "2 лк,         6 пр"
        },
        {
            "name": "История и методология юридической науки",
            "teacher": "Ахмедов Р.М.",
            "type": "2 лк,        6 пр"
        },
        {
            "name": "Интеллектуальная собственность в предпринимательской деятельности",
            "teacher": "Джинджолия Р.С.",
            "type": [
                "1",
                "лк,",
                "6",
                "пр"
            ]
        },
        {
            "name": "Противодействие коррупции в сфере экономики и гос. закупок",
            "teacher": "Джинджолия Р.С.",
            "type": "2 лк, 6 пр"
        },
        {
            "name": "Основы корпоративного права",
            "teacher": "Джинджолия Р.С.",
            "type": [
                "1",
                "лк,",
                "4",
                "пр"
            ]
        },
        {
            "name": "Иностранный язык ",
            "teacher": "Еремкина Н.И.",
            "type": "пр"
        },
        {
            "name": "Теория и практика правового рег. предпринимательской деятельности",
            "teacher": "Джинджолия Р.С.",
            "type": [
                "1",
                "лк,",
                "4",
                "пр"
            ]
        },
        {
            "name": "Сравнительное поведение",
            "teacher": "Джинджолия Р.С.",
            "type": [
                "1",
                "лк,",
                "2",
                "пр"
            ]
        },
        {
            "name": "Защита прав предпринимателей",
            "teacher": "Джинджолия Р.С.",
            "type": [
                "1",
                "лк,",
                "4",
                "пр"
            ]
        },
        {
            "name": "Сравнительное поведение",
            "teacher": "Джинджолия Р.С.",
            "type": [
                "1",
                "лаб,",
                "2",
                "пр"
            ]
        }
    ],
    "timetables": [
        {
            "days": [
                {
                    "lessons": [
                        {
                            "lessonNumber": 1,
                            "subjectIndex": 0,
                            "constraint": {
                                "type": [],
                                "weeks": []
                            },
                            "room": "nan",
                            "locationIndex": 0
                        },
                        {
                            "lessonNumber": 2,
                            "subjectIndex": 0,
                            "constraint": {
                                "type": [],
                                "weeks": []
                            },
                            "room": "nan",
                            "locationIndex": 0
                        },
                        {
                            "lessonNumber": 3,
                            "subjectIndex": 1,
                            "constraint": {
                                "type": "н",
                                "weeks": [
                                    "3",
                                    "5",
                                    "7",
                                    "9"
                                ]
                            },
                            "room": "Д",
                            "locationIndex": -1
                        },
                        {
                            "lessonNumber": 4,
                            "subjectIndex": 0,
                            "constraint": {
                                "type": [],
                                "weeks": []
                            },
                            "room": "nan",
                            "locationIndex": 0
                        },
                        {
                            "lessonNumber": 5,
                            "subjectIndex": 1,
                            "constraint": {
                                "type": "н",
                                "weeks": [
                                    "3",
                                    "5",
                                    "7",
                                    "9"
                                ]
                            },
                            "room": "Д",
                            "locationIndex": -1
                        },
                        {
                            "lessonNumber": 6,
                            "subjectIndex": 3,
                            "constraint": {
                                "type": [],
                                "weeks": []
                            },
                            "room": "Д",
                            "locationIndex": -1
                        }
                    ]
                },
                {
                    "lessons": [
                        {
                            "lessonNumber": 1,
                            "subjectIndex": 0,
                            "constraint": {
                                "type": [],
                                "weeks": []
                            },
                            "room": "nan",
                            "locationIndex": 0
                        },
                        {
                            "lessonNumber": 2,
                            "subjectIndex": 0,
                            "constraint": {
                                "type": [],
                                "weeks": []
                            },
                            "room": "nan",
                            "locationIndex": 0
                        },
                        {
                            "lessonNumber": 3,
                            "subjectIndex": 0,
                            "constraint": {
                                "type": [],
                                "weeks": []
                            },
                            "room": "nan",
                            "locationIndex": 0
                        },
                        {
                            "lessonNumber": 4,
                            "subjectIndex": 0,
                            "constraint": {
                                "type": [],
                                "weeks": []
                            },
                            "room": "nan",
                            "locationIndex": 0
                        },
                        {
                            "lessonNumber": 5,
                            "subjectIndex": 0,
                            "constraint": {
                                "type": [],
                                "weeks": []
                            },
                            "room": "nan",
                            "locationIndex": 0
                        },
                        {
                            "lessonNumber": 6,
                            "subjectIndex": 5,
                            "constraint": {
                                "type": "н",
                                "weeks": [
                                    "кр1"
                                ]
                            },
                            "room": "Д",
                            "locationIndex": -1
                        }
                    ]
                },
                {
                    "lessons": [
                        {
                            "lessonNumber": 1,
                            "subjectIndex": 6,
                            "constraint": {
                                "type": [],
                                "weeks": []
                            },
                            "room": "Д",
                            "locationIndex": -1
                        },
                        {
                            "lessonNumber": 2,
                            "subjectIndex": 5,
                            "constraint": {
                                "type": "н",
                                "weeks": [
                                    "кр1"
                                ]
                            },
                            "room": "Д",
                            "locationIndex": -1
                        },
                        {
                            "lessonNumber": 3,
                            "subjectIndex": 0,
                            "constraint": {
                                "type": [],
                                "weeks": []
                            },
                            "room": "nan",
                            "locationIndex": 0
                        },
                        {
                            "lessonNumber": 4,
                            "subjectIndex": 0,
                            "constraint": {
                                "type": [],
                                "weeks": []
                            },
                            "room": "nan",
                            "locationIndex": 0
                        },
                        {
                            "lessonNumber": 5,
                            "subjectIndex": 0,
                            "constraint": {
                                "type": [],
                                "weeks": []
                            },
                            "room": "nan",
                            "locationIndex": 0
                        },
                        {
                            "lessonNumber": 6,
                            "subjectIndex": 0,
                            "constraint": {
                                "type": [],
                                "weeks": []
                            },
                            "room": "nan",
                            "locationIndex": 0
                        }
                    ]
                },
                {
                    "lessons": [
                        {
                            "lessonNumber": 1,
                            "subjectIndex": 0,
                            "constraint": {
                                "type": [],
                                "weeks": []
                            },
                            "room": "nan",
                            "locationIndex": 0
                        },
                        {
                            "lessonNumber": 2,
                            "subjectIndex": 7,
                            "constraint": {
                                "type": "н",
                                "weeks": [
                                    "кр",
                                    ".",
                                    "1",
                                    "13",
                                    "15"
                                ]
                            },
                            "room": "Д",
                            "locationIndex": -1
                        },
                        {
                            "lessonNumber": 3,
                            "subjectIndex": 0,
                            "constraint": {
                                "type": [],
                                "weeks": []
                            },
                            "room": "nan",
                            "locationIndex": 0
                        },
                        {
                            "lessonNumber": 4,
                            "subjectIndex": 0,
                            "constraint": {
                                "type": [],
                                "weeks": []
                            },
                            "room": "nan",
                            "locationIndex": 0
                        },
                        {
                            "lessonNumber": 5,
                            "subjectIndex": 8,
                            "constraint": {
                                "type": [],
                                "weeks": []
                            },
                            "room": "Д",
                            "locationIndex": -1
                        },
                        {
                            "lessonNumber": 6,
                            "subjectIndex": 9,
                            "constraint": {
                                "type": "н",
                                "weeks": [
                                    "кр",
                                    ".",
                                    "11",
                                    "13",
                                    "15"
                                ]
                            },
                            "room": "Д",
                            "locationIndex": -1
                        }
                    ]
                },
                {
                    "lessons": [
                        {
                            "lessonNumber": 1,
                            "subjectIndex": 11,
                            "constraint": {
                                "type": "н",
                                "weeks": [
                                    "кр12",
                                    "14",
                                    "16"
                                ]
                            },
                            "room": "Д",
                            "locationIndex": -1
                        },
                        {
                            "lessonNumber": 2,
                            "subjectIndex": 9,
                            "constraint": {
                                "type": "н",
                                "weeks": [
                                    "кр",
                                    ".",
                                    "11",
                                    "13",
                                    "15"
                                ]
                            },
                            "room": "Д",
                            "locationIndex": -1
                        },
                        {
                            "lessonNumber": 3,
                            "subjectIndex": 11,
                            "constraint": {
                                "type": "н",
                                "weeks": [
                                    "кр12",
                                    "14",
                                    "16"
                                ]
                            },
                            "room": "Д",
                            "locationIndex": -1
                        },
                        {
                            "lessonNumber": 4,
                            "subjectIndex": 0,
                            "constraint": {
                                "type": [],
                                "weeks": []
                            },
                            "room": "nan",
                            "locationIndex": 0
                        },
                        {
                            "lessonNumber": 5,
                            "subjectIndex": 0,
                            "constraint": {
                                "type": [],
                                "weeks": []
                            },
                            "room": "nan",
                            "locationIndex": 0
                        },
                        {
                            "lessonNumber": 6,
                            "subjectIndex": 0,
                            "constraint": {
                                "type": [],
                                "weeks": []
                            },
                            "room": "nan",
                            "locationIndex": 0
                        }
                    ]
                },
                {
                    "lessons": [
                        {
                            "lessonNumber": 1,
                            "subjectIndex": 0,
                            "constraint": {
                                "type": [],
                                "weeks": []
                            },
                            "room": "nan",
                            "locationIndex": 0
                        },
                        {
                            "lessonNumber": 2,
                            "subjectIndex": 0,
                            "constraint": {
                                "type": [],
                                "weeks": []
                            },
                            "room": "nan",
                            "locationIndex": 0
                        },
                        {
                            "lessonNumber": 3,
                            "subjectIndex": 0,
                            "constraint": {
                                "type": [],
                                "weeks": []
                            },
                            "room": "nan",
                            "locationIndex": 0
                        },
                        {
                            "lessonNumber": 4,
                            "subjectIndex": 0,
                            "constraint": {
                                "type": [],
                                "weeks": []
                            },
                            "room": "nan",
                            "locationIndex": 0
                        },
                        {
                            "lessonNumber": 5,
                            "subjectIndex": 0,
                            "constraint": {
                                "type": [],
                                "weeks": []
                            },
                            "room": "nan",
                            "locationIndex": 0
                        },
                        {
                            "lessonNumber": 6,
                            "subjectIndex": 0,
                            "constraint": {
                                "type": [],
                                "weeks": []
                            },
                            "room": "nan",
                            "locationIndex": 0
                        }
                    ]
                }
            ]
        },
        {
            "days": [
                {
                    "lessons": [
                        {
                            "lessonNumber": 1,
                            "subjectIndex": 0,
                            "constraint": {
                                "type": [],
                                "weeks": []
                            },
                            "room": "nan",
                            "locationIndex": 0
                        },
                        {
                            "lessonNumber": 2,
                            "subjectIndex": 0,
                            "constraint": {
                                "type": [],
                                "weeks": []
                            },
                            "room": "nan",
                            "locationIndex": 0
                        },
                        {
                            "lessonNumber": 3,
                            "subjectIndex": 2,
                            "constraint": {
                                "type": "н",
                                "weeks": [
                                    "13",
                                    "15"
                                ]
                            },
                            "room": "Д",
                            "locationIndex": -1
                        },
                        {
                            "lessonNumber": 4,
                            "subjectIndex": 0,
                            "constraint": {
                                "type": [],
                                "weeks": []
                            },
                            "room": "nan",
                            "locationIndex": 0
                        },
                        {
                            "lessonNumber": 5,
                            "subjectIndex": 2,
                            "constraint": {
                                "type": "н",
                                "weeks": [
                                    "13",
                                    "15"
                                ]
                            },
                            "room": "Д",
                            "locationIndex": -1
                        },
                        {
                            "lessonNumber": 6,
                            "subjectIndex": 0,
                            "constraint": {
                                "type": [],
                                "weeks": []
                            },
                            "room": "nan",
                            "locationIndex": 0
                        }
                    ]
                },
                {
                    "lessons": [
                        {
                            "lessonNumber": 1,
                            "subjectIndex": 4,
                            "constraint": {
                                "type": [],
                                "weeks": []
                            },
                            "room": "Д",
                            "locationIndex": -1
                        },
                        {
                            "lessonNumber": 2,
                            "subjectIndex": 0,
                            "constraint": {
                                "type": [],
                                "weeks": []
                            },
                            "room": "nan",
                            "locationIndex": 0
                        },
                        {
                            "lessonNumber": 3,
                            "subjectIndex": 0,
                            "constraint": {
                                "type": [],
                                "weeks": []
                            },
                            "room": "nan",
                            "locationIndex": 0
                        },
                        {
                            "lessonNumber": 4,
                            "subjectIndex": 0,
                            "constraint": {
                                "type": [],
                                "weeks": []
                            },
                            "room": "nan",
                            "locationIndex": 0
                        },
                        {
                            "lessonNumber": 5,
                            "subjectIndex": 0,
                            "constraint": {
                                "type": [],
                                "weeks": []
                            },
                            "room": "nan",
                            "locationIndex": 0
                        },
                        {
                            "lessonNumber": 6,
                            "subjectIndex": 0,
                            "constraint": {
                                "type": [],
                                "weeks": []
                            },
                            "room": "nan",
                            "locationIndex": 0
                        }
                    ]
                },
                {
                    "lessons": [
                        {
                            "lessonNumber": 1,
                            "subjectIndex": 0,
                            "constraint": {
                                "type": [],
                                "weeks": []
                            },
                            "room": "nan",
                            "locationIndex": 0
                        },
                        {
                            "lessonNumber": 2,
                            "subjectIndex": 6,
                            "constraint": {
                                "type": [],
                                "weeks": []
                            },
                            "room": "Д",
                            "locationIndex": -1
                        },
                        {
                            "lessonNumber": 3,
                            "subjectIndex": 0,
                            "constraint": {
                                "type": [],
                                "weeks": []
                            },
                            "room": "nan",
                            "locationIndex": 0
                        },
                        {
                            "lessonNumber": 4,
                            "subjectIndex": 0,
                            "constraint": {
                                "type": [],
                                "weeks": []
                            },
                            "room": "nan",
                            "locationIndex": 0
                        },
                        {
                            "lessonNumber": 5,
                            "subjectIndex": 0,
                            "constraint": {
                                "type": [],
                                "weeks": []
                            },
                            "room": "nan",
                            "locationIndex": 0
                        },
                        {
                            "lessonNumber": 6,
                            "subjectIndex": 7,
                            "constraint": {
                                "type": "н",
                                "weeks": [
                                    "кр",
                                    ".",
                                    "1",
                                    "13",
                                    "15"
                                ]
                            },
                            "room": "Д",
                            "locationIndex": -1
                        }
                    ]
                },
                {
                    "lessons": [
                        {
                            "lessonNumber": 1,
                            "subjectIndex": 0,
                            "constraint": {
                                "type": [],
                                "weeks": []
                            },
                            "room": "nan",
                            "locationIndex": 0
                        },
                        {
                            "lessonNumber": 2,
                            "subjectIndex": 0,
                            "constraint": {
                                "type": [],
                                "weeks": []
                            },
                            "room": "nan",
                            "locationIndex": 0
                        },
                        {
                            "lessonNumber": 3,
                            "subjectIndex": 0,
                            "constraint": {
                                "type": [],
                                "weeks": []
                            },
                            "room": "nan",
                            "locationIndex": 0
                        },
                        {
                            "lessonNumber": 4,
                            "subjectIndex": 0,
                            "constraint": {
                                "type": [],
                                "weeks": []
                            },
                            "room": "nan",
                            "locationIndex": 0
                        },
                        {
                            "lessonNumber": 5,
                            "subjectIndex": 8,
                            "constraint": {
                                "type": [],
                                "weeks": []
                            },
                            "room": "Д",
                            "locationIndex": -1
                        },
                        {
                            "lessonNumber": 6,
                            "subjectIndex": 10,
                            "constraint": {
                                "type": "н",
                                "weeks": [
                                    "11",
                                    "13",
                                    "15"
                                ]
                            },
                            "room": "Д",
                            "locationIndex": -1
                        }
                    ]
                },
                {
                    "lessons": [
                        {
                            "lessonNumber": 1,
                            "subjectIndex": 12,
                            "constraint": {
                                "type": "н",
                                "weeks": [
                                    "12",
                                    "14",
                                    "16"
                                ]
                            },
                            "room": "Д",
                            "locationIndex": -1
                        },
                        {
                            "lessonNumber": 2,
                            "subjectIndex": 12,
                            "constraint": {
                                "type": "н",
                                "weeks": [
                                    "11",
                                    "13",
                                    "15"
                                ]
                            },
                            "room": "Д",
                            "locationIndex": -1
                        },
                        {
                            "lessonNumber": 3,
                            "subjectIndex": 12,
                            "constraint": {
                                "type": "н",
                                "weeks": [
                                    "12",
                                    "14",
                                    "16"
                                ]
                            },
                            "room": "Д",
                            "locationIndex": -1
                        },
                        {
                            "lessonNumber": 4,
                            "subjectIndex": 0,
                            "constraint": {
                                "type": [],
                                "weeks": []
                            },
                            "room": "nan",
                            "locationIndex": 0
                        },
                        {
                            "lessonNumber": 5,
                            "subjectIndex": 0,
                            "constraint": {
                                "type": [],
                                "weeks": []
                            },
                            "room": "nan",
                            "locationIndex": 0
                        },
                        {
                            "lessonNumber": 6,
                            "subjectIndex": 0,
                            "constraint": {
                                "type": [],
                                "weeks": []
                            },
                            "room": "nan",
                            "locationIndex": 0
                        }
                    ]
                },
                {
                    "lessons": [
                        {
                            "lessonNumber": 1,
                            "subjectIndex": 0,
                            "constraint": {
                                "type": [],
                                "weeks": []
                            },
                            "room": "nan",
                            "locationIndex": 0
                        },
                        {
                            "lessonNumber": 2,
                            "subjectIndex": 0,
                            "constraint": {
                                "type": [],
                                "weeks": []
                            },
                            "room": "nan",
                            "locationIndex": 0
                        },
                        {
                            "lessonNumber": 3,
                            "subjectIndex": 0,
                            "constraint": {
                                "type": [],
                                "weeks": []
                            },
                            "room": "nan",
                            "locationIndex": 0
                        },
                        {
                            "lessonNumber": 4,
                            "subjectIndex": 0,
                            "constraint": {
                                "type": [],
                                "weeks": []
                            },
                            "room": "nan",
                            "locationIndex": 0
                        },
                        {
                            "lessonNumber": 5,
                            "subjectIndex": 0,
                            "constraint": {
                                "type": [],
                                "weeks": []
                            },
                            "room": "nan",
                            "locationIndex": 0
                        },
                        {
                            "lessonNumber": 6,
                            "subjectIndex": 0,
                            "constraint": {
                                "type": [],
                                "weeks": []
                            },
                            "room": "nan",
                            "locationIndex": 0
                        }
                    ]
                }
            ]
        }
    ]
}